spygrt/__init__.py
spygrt/calibration.py
spygrt/stream.py
spygrt/tracker.py
spygrt-1.0.0.dist-info/METADATA
spygrt-1.0.0.dist-info/WHEEL
spygrt-1.0.0.dist-info/licenses/LICENSE
spygrt-1.0.0.dist-info/RECORD
