Metadata-Version: 2.3
Name: SpyGRT
Version: 1.0.0
Summary: Toolkit to build SGRT applications
Project-URL: Download, https://github.com/Image-X-Institute/SpyGRT/archive/refs/tags/v_1.0.0.tar.gz
Project-URL: Homepage, https://github.com/ACRF-Image-X-Institute/SpyGRT
Author-email: Youssef Ben Bouchta <youssef.benbouchta@sydney.edu.au>
License: MIT License
License-File: LICENSE
Keywords: SGRT,radiation-oncology,radiotherapy,realsense
Requires-Python: <3.12,>=3.7
Requires-Dist: numpy
Requires-Dist: open3d>=0.17
Requires-Dist: opencv-python
Requires-Dist: pyrealsense2
